.travis.yml
.version
AUTHORS
CONTRIBUTING.md
COPYING
ChangeLog
INSTALL
MANIFEST
MANIFEST.in
Makefile.am
Makefile.in
NEWS
PKG-INFO
README
aclocal.m4
build-aux/compile
build-aux/config.guess
build-aux/config.sub
build-aux/depcomp
build-aux/install-sh
build-aux/ltmain.sh
build-aux/missing
build-aux/py-compile
build-aux/tap-driver.sh
build-aux/test-driver
config.h.in
configure
configure.ac
dbus-gmain/AUTHORS
dbus-gmain/CONTRIBUTING.md
dbus-gmain/COPYING
dbus-gmain/Makefile.am
dbus-gmain/Makefile.in
dbus-gmain/README.md
dbus-gmain/dbus-gmain.c
dbus-gmain/dbus-gmain.h
dbus-gmain/tests/30574.c
dbus-gmain/tests/test-thread-client.c
dbus-gmain/tests/test-thread-server.c
dbus-gmain/tests/test-thread.h
dbus-gmain/tests/util.c
dbus-gmain/tests/util.h
dbus-python.pc.in
dbus/__init__.py
dbus/_compat.py
dbus/_dbus.py
dbus/_expat_introspect_parser.py
dbus/bus.py
dbus/connection.py
dbus/decorators.py
dbus/exceptions.py
dbus/gi_service.py
dbus/glib.py
dbus/gobject_service.py
dbus/lowlevel.py
dbus/mainloop/__init__.py
dbus/mainloop/glib.py
dbus/proxies.py
dbus/server.py
dbus/service.py
dbus/types.py
dbus_bindings/abstract.c
dbus_bindings/bus.c
dbus_bindings/bytes.c
dbus_bindings/compat-internal.h
dbus_bindings/conn-internal.h
dbus_bindings/conn-methods.c
dbus_bindings/conn.c
dbus_bindings/containers.c
dbus_bindings/dbus_bindings-internal.h
dbus_bindings/debug.c
dbus_bindings/exceptions.c
dbus_bindings/float.c
dbus_bindings/generic.c
dbus_bindings/int.c
dbus_bindings/libdbusconn.c
dbus_bindings/mainloop.c
dbus_bindings/message-append.c
dbus_bindings/message-get-args.c
dbus_bindings/message-internal.h
dbus_bindings/message.c
dbus_bindings/module.c
dbus_bindings/pending-call.c
dbus_bindings/server.c
dbus_bindings/signature.c
dbus_bindings/string.c
dbus_bindings/types-internal.h
dbus_bindings/unixfd.c
dbus_bindings/validation.c
dbus_glib_bindings/module.c
dbus_python.egg-info/PKG-INFO
dbus_python.egg-info/SOURCES.txt
dbus_python.egg-info/dependency_links.txt
dbus_python.egg-info/top_level.txt
doc/API_CHANGES.txt
doc/PY3PORT.txt
doc/_static/.gitignore
doc/conf.py
doc/dbus.bus.rst
doc/dbus.connection.rst
