Metadata-Version: 1.2
Name: dbus-python
Version: 1.2.10
Summary: Python bindings for libdbus
Home-page: http://www.freedesktop.org/wiki/Software/DBusBindings/#python
Maintainer: The D-Bus maintainers
Maintainer-email: dbus@lists.freedesktop.org
License: Expat (MIT/X11)
Download-URL: http://dbus.freedesktop.org/releases/dbus-python/
Platform: UNKNOWN
Classifier: Development Status :: 7 - Inactive
Classifier: License :: OSI Approved :: MIT License
Classifier: Programming Language :: C
Classifier: Programming Language :: Python :: 2
Classifier: Programming Language :: Python :: 3
Classifier: Programming Language :: Python :: Implementation :: CPython
Classifier: Topic :: Software Development :: Object Brokering
